cubetranslate/__init__.py
cubetranslate/constants.py
cubetranslate/run_packaged_model.py
cubetranslate/translate_pack.py
cubetranslate/translate_service.py
cubetranslate-0.0.2.dist-info/LICENSE
cubetranslate-0.0.2.dist-info/METADATA
cubetranslate-0.0.2.dist-info/WHEEL
cubetranslate-0.0.2.dist-info/top_level.txt
cubetranslate-0.0.2.dist-info/zip-safe
cubetranslate-0.0.2.dist-info/RECORD
